{
  "chapters": [
    {
      "number": "1",
      "title": "The Comprehensive Guide to Apples: From Orchard to Table",
      "subsections": [
        {
          "number": "1.1",
          "title": "A Fruitful Introduction: Unveiling the Apple's Allure",
          "subsections": [
            {
              "number": "1.1.1",
              "title": "A Bite of History: Tracing the Apple's Ancient Roots"
            },
            {
              "number": "1.1.2",
              "title": "Nutritional Powerhouse: Exploring the Apple's Health Benefits"
            },
            {
              "number": "1.1.3",
              "title": "Apples Around the World: A Global Perspective"
            }
          ]
        },
        {
          "number": "1.2",
          "title": "Cultivating Excellence: The Art and Science of Apple Growing",
          "subsections": [
            {
              "number": "1.2.1",
              "title": "Orchard Planning and Preparation: Laying the Foundation for Success"
            }
          ]
        }
      ]
    }
  ]
}