{
  "chapters": [
    {
      "number": "1",
      "title": "Everything You Need to Know About Apples",
      "subsections": [
        {
          "number": "1.1",
          "title": "A Bite of History: Tracing the Apple's Journey Through Time",
          "subsections": [
            {
              "number": "1.1.1",
              "title": "Origins and Ancient Varieties"
            },
            {
              "number": "1.1.2",
              "title": "Apples in Mythology and Folklore"
            },
            {
              "number": "1.1.3",
              "title": "The Spread of Apples Around the World"
            }
          ]
        },
        {
          "number": "1.2",
          "title": "Apple Varieties: A World of Flavors",
          "subsections": [
            {
              "number": "1.2.1",
              "title": "Popular Varieties: Granny Smith, Fuji, Gala, Honeycrisp, and More"
            },
            {
              "number": "1.2.2",
              "title": "Heirloom Apples: Rediscovering Forgotten Flavors"
            },
            {
              "number": "1.2.3",
              "title": "Choosing the Right Apple for Your Needs: Sweetness, Tartness, and Texture"
            }
          ]
        },
        {
          "number": "1.3",
          "title": "The Science of Apples: Nutrition and Health Benefits",
          "subsections": [
            {
              "number": "1.3.1",
              "title": "Nutritional Value: Vitamins, Minerals, and Fiber"
            },
            {
              "number": "1.3.2",
              "title": "Health Benefits: Heart Health, Cancer Prevention, and More"
            },
            {
              "number": "1.3.3",
              "title": "Apples and Digestion: The Role of Pectin"
            }
          ]
        },
        {
          "number": "1.4",
          "title": "Growing Your Own Apples: A Beginner's Guide",
          "subsections": [
            {
              "number": "1.4.1",
              "title": "Choosing the Right Tree: Variety, Rootstock, and Climate"
            },
            {
              "number": "1.4.2",
              "title": "Planting and Care: Soil, Sunlight, and Watering"
            },
            {
              "number": "1.4.3",
              "title": "Pruning and Training: Shaping Your Tree for Optimal Fruit Production"
            },
            {
              "number": "1.4.4",
              "title": "Pest and Disease Management: Organic and Sustainable Approaches"
            },
            {
              "number": "1.4.5",
              "title": "Harvesting and Storage: Ensuring a Bountiful Crop"
            }
          ]
        },
        {
          "number": "1.5",
          "title": "Apples in the Kitchen: Recipes and Culinary Uses",
          "subsections": [
            {
              "number": "1.5.1",
              "title": "Sweet Treats: Apple Pie, Apple Crisp, Apple Cake, and More"
            },
            {
              "number": "1.5.2",
              "title": "Savory Dishes: Apple Sauce, Apple Chutney, and Apple Salads"
            },
            {
              "number": "1.5.3",
              "title": "Apple Beverages: Apple Cider, Apple Juice, and Hard Cider"
            },
            {
              "number": "1.5.4",
              "title": "Tips and Tricks: Preparing and Cooking with Apples"
            }
          ]
        },
        {
          "number": "1.6",
          "title": "Beyond the Fruit: Using Apples in Crafts and Other Applications",
          "subsections": [
            {
              "number": "1.6.1",
              "title": "Apple Prints and Decorations"
            },
            {
              "number": "1.6.2",
              "title": "Apple Cider Vinegar: Uses and Benefits"
            },
            {
              "number": "1.6.3",
              "title": "Apple Peels and Cores: Reducing Waste and Composting"
            }
          ]
        }
      ]
    }
  ]
}